README.md
setup.py
pychromepdf/__init__.py
pychromepdf/chrome_pdf.py
pychromepdf.egg-info/PKG-INFO
pychromepdf.egg-info/SOURCES.txt
pychromepdf.egg-info/dependency_links.txt
pychromepdf.egg-info/top_level.txt