Metadata-Version: 2.1
Name: pychromepdf
Version: 1.0
Summary: Creates PDFs from HTML rendered using chrome or chromium
Home-page: https://github.com/nvnmo/pychromepdf
Author: Navin Mohan
Author-email: navinmohan81@gmail.com
License: UNKNOWN
Platform: UNKNOWN
Classifier: Programming Language :: Python :: 3
Classifier: License :: OSI Approved :: MIT License
Classifier: Operating System :: OS Independent
Classifier: Development Status :: 4 - Beta
